hints.py
hints_mod-0.0.2.dist-info/LICENSE
hints_mod-0.0.2.dist-info/METADATA
hints_mod-0.0.2.dist-info/WHEEL
hints_mod-0.0.2.dist-info/top_level.txt
hints_mod-0.0.2.dist-info/RECORD
