Metadata-Version: 2.1
Name: hints-mod
Version: 0.0.2
Summary: A simple tool for creating a searchable 'hints' sqlite3 database
Home-page: https://github.com/ejohnfel/hints
Author: Eric Johnfelt
Author-email: ejohnfel@hotmail.com
License: UNKNOWN
Project-URL: Bug Tracker, https://github.com/ejohnfel/hints/issues
Platform: UNKNOWN
Classifier: Programming Language :: Python :: 3
Classifier: License :: OSI Approved :: MIT License
Classifier: Operating System :: OS Independent
Requires-Python: >=3.0
License-File: LICENSE
Requires-Dist: py-helper-mod
Requires-Dist: mysqlite3-mod
